perceval_finos-0.1.11-py3.6-nspkg.pth
perceval/backends/finos/__init__.py
perceval/backends/finos/finosmeetings.py
perceval_finos-0.1.11.dist-info/AUTHORS
perceval_finos-0.1.11.dist-info/LICENSE
perceval_finos-0.1.11.dist-info/METADATA
perceval_finos-0.1.11.dist-info/WHEEL
perceval_finos-0.1.11.dist-info/namespace_packages.txt
perceval_finos-0.1.11.dist-info/top_level.txt
perceval_finos-0.1.11.dist-info/RECORD
