Metadata-Version: 2.1
Name: perceval-finos
Version: 0.1.11
Summary: Bundle of Perceval backends for FINOS ecosystem
Home-page: https://github.com/Bitergia/grimoirelab-perceval-finos
Author: Bitergia
Author-email: sduenas@bitergia.com
License: GPLv3
Keywords: development repositories analytics finos
Platform: UNKNOWN
Classifier: Development Status :: 5 - Production/Stable
Classifier: Intended Audience :: Developers
Classifier: Topic :: Software Development
Classifier: License :: OSI Approved :: GNU General Public License v3 or later (GPLv3+)
Classifier: Programming Language :: Python :: 3
License-File: LICENSE
License-File: AUTHORS
Requires-Dist: requests (>=2.7.0)
Requires-Dist: grimoirelab-toolkit (>=0.1.9)
Requires-Dist: perceval (>=0.12.12)
